cf_nlp-0.1.18.dist-info/METADATA
cf_nlp-0.1.18.dist-info/RECORD
cf_nlp-0.1.18.dist-info/WHEEL
cf_nlp-0.1.18.dist-info/top_level.txt
nlp/__init__.py
nlp/dl_architecture.py
nlp/gender_classification.py
nlp/interaction_views.py
nlp/language_variety.py
nlp/library.py
nlp/nlp.py
nlp/redi.py
nlp/reldi_tagger.py
nlp/reldi_tokenizer.py
nlp/sentiment_analysis.py
nlp/settings.py
nlp/terminology.py
nlp/tweetcat.py
nlp/visualization_views.py
nlp/db/package_data.json
nlp/package_data/categories/15acb469-c510-44f0-8330-60bfe11a463c.json
nlp/package_data/categories/9a30eafc-37b8-48f2-8a92-692c4b324dff.json
nlp/package_data/widgets/02fa24e1-6875-4007-8b90-70e6b72e20d5.json
nlp/package_data/widgets/09d72ebd-2eaf-47f6-95e0-2f2ed0c51ea2.json
nlp/package_data/widgets/0a724ff0-2748-4c29-b0aa-cc19180eae79.json
nlp/package_data/widgets/0a85e4da-16f8-4731-878c-6c7f2e8824e3.json
nlp/package_data/widgets/0c278bb4-5fbb-4260-84ab-631faae74d87.json
nlp/package_data/widgets/0edb0651-f5a9-489c-9fa0-1604c23a1a0b.json
nlp/package_data/widgets/113750d0-b8ca-4cff-8201-90e38afb0f62.json
nlp/package_data/widgets/1d2e12a0-3f5d-44b6-a3c5-c87e4eaf3a24.json
nlp/package_data/widgets/1e75106f-ba4c-4b2b-a8cf-fb0f9c1d42f8.json
nlp/package_data/widgets/22475bd3-552f-4c5a-9e21-353e439b9067.json
nlp/package_data/widgets/25c283b6-fa7d-44aa-9452-a3ccb4972285.json
nlp/package_data/widgets/27273666-764d-458d-9513-0715ba2e6b4d.json
nlp/package_data/widgets/28afbde5-ed3b-4ec5-88c2-650bb7de15c9.json
nlp/package_data/widgets/29de3489-4fc2-4f5c-a42d-79f8b4d9178e.json
nlp/package_data/widgets/3515df45-45c1-4987-a056-c9fcf527b217.json
nlp/package_data/widgets/3c7a62d5-8f48-4c82-84f1-9ce5e2738772.json
nlp/package_data/widgets/4414ef0d-4dde-46ee-ba7b-12da93daef15.json
nlp/package_data/widgets/49fec9dc-71e0-4af0-bc3a-efda101babb3.json
nlp/package_data/widgets/4eec620e-f919-47d5-99f9-846ada308ac2.json
nlp/package_data/widgets/4f8745f5-8a11-4311-883b-eb9e19302ef9.json
nlp/package_data/widgets/5524d708-aa5f-416e-b60f-2ece998205e0.json
nlp/package_data/widgets/5c7768f9-4449-469b-bae1-f56e9e48be34.json
