Metadata-Version: 2.1
Name: cf-nlp
Version: 0.1.18
Summary: ClowdFlows natural language processing module
Home-page: https://github.com/xflows/cf_nlp
Author: Matej Martinc
Author-email: matej.martinc@ijs.si
License: MIT License
Platform: UNKNOWN
Classifier: Development Status :: 2 - Pre-Alpha
Classifier: Environment :: Web Environment
Classifier: Framework :: Django
Classifier: Intended Audience :: Developers
Classifier: License :: OSI Approved :: MIT License
Classifier: Operating System :: OS Independent
Classifier: Programming Language :: Python
Classifier: Programming Language :: Python :: 2
Classifier: Topic :: Internet :: WWW/HTTP
Classifier: Topic :: Internet :: WWW/HTTP :: Dynamic Content
Classifier: Topic :: Scientific/Engineering :: Artificial Intelligence
Classifier: Topic :: Software Development :: Libraries
Requires-Dist: pandas (==0.20.1)
Requires-Dist: langid (==1.1.6)
Requires-Dist: tweepy (==3.5.0)
Requires-Dist: marisa-trie (==0.7.4)
Requires-Dist: python-crfsuite (==0.9)
Requires-Dist: reldi (==1.6)
Requires-Dist: theano
Requires-Dist: keras (==2.2.2)
Requires-Dist: lemmagen (==1.2.0)
Requires-Dist: editdistance (==0.4)
